LICENSE
MANIFEST.in
README.md
setup.py
stupidpackage/__init__.py
stupidpackage/api_helper.py
stupidpackage/configuration.py
stupidpackage/decorators.py
stupidpackage/stupidpackage_client.py
stupidpackage.egg-info/PKG-INFO
stupidpackage.egg-info/SOURCES.txt
stupidpackage.egg-info/dependency_links.txt
stupidpackage.egg-info/requires.txt
stupidpackage.egg-info/top_level.txt
stupidpackage/controllers/__init__.py
stupidpackage/controllers/base_controller.py
stupidpackage/controllers/pet_controller.py
stupidpackage/controllers/store_controller.py
stupidpackage/controllers/user_controller.py
stupidpackage/exceptions/__init__.py
stupidpackage/exceptions/api_exception.py
stupidpackage/http/__init__.py
stupidpackage/http/http_call_back.py
stupidpackage/http/http_client.py
stupidpackage/http/http_context.py
stupidpackage/http/http_method_enum.py
stupidpackage/http/http_request.py
stupidpackage/http/http_response.py
stupidpackage/http/requests_client.py
stupidpackage/models/__init__.py
stupidpackage/models/api_response.py
stupidpackage/models/category.py
stupidpackage/models/o_auth_scope_enum.py
stupidpackage/models/order.py
stupidpackage/models/pet.py
stupidpackage/models/status_6_enum.py
stupidpackage/models/status_enum.py
stupidpackage/models/tag.py
stupidpackage/models/user.py